Metadata-Version: 2.1
Name: DjangoPackage-v0.2.1
Version: 0.2.1
Summary: UNKNOWN
Home-page: https://github.com/KathurimaKimathi/DjangoPackage/
Author: Kathurima Kimathi
Author-email: kathurima@healthcloud.co.ke
License: UNKNOWN
Keywords: sample djangopackage setuptools development
Platform: UNKNOWN
Classifier: Development Status :: 3 - Alpha
Classifier: Intended Audience :: Developers
Classifier: Topic :: Software Development :: Build Tools
Classifier: License :: OSI Approved :: MIT License
Classifier: Programming Language :: Python :: 2
Classifier: Programming Language :: Python :: 2.7
Classifier: Programming Language :: Python :: 3
Classifier: Programming Language :: Python :: 3.4
Classifier: Programming Language :: Python :: 3.5
Classifier: Programming Language :: Python :: 3.6
Classifier: Programming Language :: Python :: 3.7
Requires-Python: >=2.7, !=3.0.*, !=3.1.*, !=3.2.*, !=3.3.*, <4
Provides-Extra: test
Provides-Extra: dev
